adr_config.py
adr_init.py
adr_list.py
adr_new.py
adr_func/__init__.py
adr_func/adr_util.py
adr_func/template.md
adr_tools_python-1.0.3.dist-info/LICENSE
adr_tools_python-1.0.3.dist-info/METADATA
adr_tools_python-1.0.3.dist-info/WHEEL
adr_tools_python-1.0.3.dist-info/entry_points.txt
adr_tools_python-1.0.3.dist-info/top_level.txt
adr_tools_python-1.0.3.dist-info/RECORD
