Metadata-Version: 2.1
Name: adr-tools-python
Version: 1.0.3
Summary: A package to provide adr-tools to python
Home-page: https://bitbucket.org/tinkerer_/adr-tools-python/
Author: Victor Sluiter
Author-email: vsluiter@yahoo.com
License: MIT
Keywords: adr,architecture decision record
Platform: UNKNOWN
Classifier: Development Status :: 5 - Production/Stable
Classifier: Intended Audience :: Developers
Classifier: Programming Language :: Python :: 3
Classifier: License :: OSI Approved :: MIT License
Classifier: Operating System :: OS Independent
Requires-Python: >=3
Requires-Dist: argparse
